survey_enhance/__init__.py
survey_enhance/impute.py
survey_enhance/percentile_match.py
survey_enhance/reweight.py
survey_enhance-0.1.4.dist-info/LICENSE
survey_enhance-0.1.4.dist-info/METADATA
survey_enhance-0.1.4.dist-info/WHEEL
survey_enhance-0.1.4.dist-info/top_level.txt
survey_enhance-0.1.4.dist-info/RECORD
