Metadata-Version: 2.1
Name: survey-enhance
Version: 0.1.4
Summary: UNKNOWN
Home-page: UNKNOWN
License: UNKNOWN
Platform: UNKNOWN
License-File: LICENSE
Requires-Dist: numpy
Requires-Dist: pandas
Requires-Dist: microdf-python
Requires-Dist: torch
Requires-Dist: policyengine-core
Requires-Dist: ipython
Requires-Dist: scikit-learn
Requires-Dist: tensorboard
Provides-Extra: dev
Requires-Dist: black ; extra == 'dev'
Requires-Dist: jupyter-book ; extra == 'dev'
Requires-Dist: sphinx <5,>=4.5.0 ; extra == 'dev'
Requires-Dist: sphinx-argparse <1,>=0.3.2 ; extra == 'dev'
Requires-Dist: sphinx-math-dollar <2,>=1.2.1 ; extra == 'dev'
Requires-Dist: furo <2023 ; extra == 'dev'
